DocOnce-1.5.15.data/scripts/doconce
doconce/DocWriter.py
doconce/__init__.p.py
doconce/__init__.py
doconce/common.py
doconce/csss.zip
doconce/cwiki.py
doconce/deck.js-latest.zip
doconce/doconce.py
doconce/doconce_config_default.py
doconce/epytext.py
doconce/expand_newcommands.py
doconce/globals.py
doconce/gwiki.py
doconce/html.py
doconce/html_images.zip
doconce/ipynb.py
doconce/jupyter_execution.py
doconce/jupyterbook.py
doconce/latex.py
doconce/latex_styles.zip
doconce/matlabnb.py
doconce/misc.py
doconce/mwiki.py
doconce/pandoc.py
doconce/pdflatex.py
doconce/plaintext.py
doconce/publish_doconce.py
doconce/reveal.js.zip
doconce/rst.py
doconce/slides.py
doconce/sphinx.py
doconce/sphinx_themes.zip
doconce/st.py
DocOnce-1.5.15.dist-info/LICENSE
DocOnce-1.5.15.dist-info/METADATA
DocOnce-1.5.15.dist-info/WHEEL
DocOnce-1.5.15.dist-info/top_level.txt
DocOnce-1.5.15.dist-info/RECORD
