Metadata-Version: 2.1
Name: DocOnce
Version: 1.5.15
Summary: Markup language similar to Markdown targeting scientific reports, software documentation, books, blog posts, and slides. DocOnce can generate LaTeX, Sphinx, HTML, IPython notebooks, Markdown, MediaWiki, and other formats
Home-page: https://github.com/doconce/doconce
Author: Hans Petter Langtangen, Alessandro Marin
Author-email: hpl@simula.no, Alessandro.Marin@fys.uio.no
Maintainer: Kristian Gregorius Hustad
Maintainer-email: krihus@ifi.uio.no
License: BSD
Project-URL: Issues on GitHub, https://github.com/doconce/doconce/issues
Classifier: Development Status :: 5 - Production/Stable
Classifier: Intended Audience :: Developers
Classifier: Intended Audience :: Education
Classifier: Intended Audience :: Other Audience
Classifier: Intended Audience :: Science/Research
Classifier: License :: OSI Approved :: BSD License
Classifier: Operating System :: MacOS
Classifier: Operating System :: Microsoft :: Windows
Classifier: Operating System :: POSIX
Classifier: Operating System :: Unix
Classifier: Programming Language :: Python
Classifier: Topic :: Documentation
Classifier: Topic :: Software Development :: Documentation
Classifier: Topic :: Text Processing :: Markup
Classifier: Topic :: Text Processing :: Markup :: HTML
Classifier: Topic :: Text Processing :: Markup :: LaTeX
Classifier: Topic :: Text Processing :: Markup :: XML
Requires-Python: >=3.6
License-File: LICENSE
Requires-Dist: pygments
Requires-Dist: preprocess
Requires-Dist: wheel
Requires-Dist: mako
Requires-Dist: future
Requires-Dist: pygments-doconce
Requires-Dist: publish-doconce
Requires-Dist: requests
Requires-Dist: nbformat
Requires-Dist: jupyter-client
Requires-Dist: regex
